extract_check_fetch_data/__init__.py
extract_check_fetch_data/main.py
extract_check_fetch_data-0.1.dist-info/METADATA
extract_check_fetch_data-0.1.dist-info/WHEEL
extract_check_fetch_data-0.1.dist-info/top_level.txt
extract_check_fetch_data-0.1.dist-info/RECORD
